logwell_client/client.py
logwell_client/handler.py
logwell_client/schema.py
logwell_client-0.1.0.dist-info/licenses/LICENCE
logwell_client-0.1.0.dist-info/METADATA
logwell_client-0.1.0.dist-info/WHEEL
logwell_client-0.1.0.dist-info/top_level.txt
logwell_client-0.1.0.dist-info/RECORD
