Metadata-Version: 2.4
Name: logwell-client
Version: 0.1.0
Summary: A hassle-free client to send logs to LogWell-service
Author-email: Amirhossein Berenji <ahberenji@gmail.com>
Requires-Python: >=3.11
License-File: LICENCE
Requires-Dist: httpx>=0.28.1
Requires-Dist: pydantic>=2.11.7
Dynamic: license-file
